[
    {
        "fix_commit_hash": "e822fb50d88152e46b70b2e26de0928d1aee3c19",
        "repo_name": "superset",
        "best_scenario_issue_date": "2017-11-07T20:26:10-08:00"
    },
    {
        "fix_commit_hash": "34278c2d56e3e3ac09660227b23fa4b107311ee5",
        "repo_name": "superset",
        "best_scenario_issue_date": "2022-07-22T01:27:29-03:00"
    },
    {
        "fix_commit_hash": "0125ba40ef31790fddbd8cd156e9d39ce532c051",
        "repo_name": "superset",
        "best_scenario_issue_date": "2019-07-03T19:55:03+03:00"
    },
    {
        "fix_commit_hash": "478d0969a8285d49636c8441472ddcbc205da672",
        "repo_name": "superset",
        "best_scenario_issue_date": "2019-08-15T20:11:05-07:00"
    },
    {
        "fix_commit_hash": "4ae77ba8aff5d9289b28eb895ce644d99886b534",
        "repo_name": "superset",
        "best_scenario_issue_date": "2017-11-20T17:34:18+01:00"
    },
    {
        "fix_commit_hash": "2fd252604689693c957a1b6875a18872a59d5ec8",
        "repo_name": "superset",
        "best_scenario_issue_date": "2016-11-01T08:17:06-07:00"
    },
    {
        "fix_commit_hash": "71c567bf3acf4716a9d982db77adbe4f4b7bbab1",
        "repo_name": "superset",
        "best_scenario_issue_date": "2020-12-03T08:46:32+00:00"
    },
    {
        "fix_commit_hash": "17cd174bbf912fe9b5406dfe125cb69ce4d2d723",
        "repo_name": "superset",
        "best_scenario_issue_date": "2020-12-17T23:04:03-08:00"
    },
    {
        "fix_commit_hash": "7ee8afb608e1251e3c2f7617fb0ae1a5340ae1a5",
        "repo_name": "superset",
        "best_scenario_issue_date": "2019-01-18T18:25:11+02:00"
    }
]