[
    {
        "fix_commit_hash": "76f9f185fb6afe04dfa2bdde190537d4007bade9",
        "repo_name": "superset",
        "best_scenario_issue_date": "2020-12-15T17:23:23-08:00"
    },
    {
        "fix_commit_hash": "7e3e13321b2b86d3a7ef1af30b5863ea9edecf05",
        "repo_name": "superset",
        "best_scenario_issue_date": "2022-10-27T21:01:36+03:00"
    },
    {
        "fix_commit_hash": "01aede0652f15e892a21c3b0c0d88db16e60b1dc",
        "repo_name": "superset",
        "best_scenario_issue_date": "2020-06-17T13:43:13-07:00"
    },
    {
        "fix_commit_hash": "0ce7fc18a883af3ba9d35a498912fcf49ab1e70c",
        "repo_name": "superset",
        "best_scenario_issue_date": "2017-01-12T12:33:06-08:00"
    },
    {
        "fix_commit_hash": "609c3594ef74ad875d1f47e7f2a4c631036503c3",
        "repo_name": "superset",
        "best_scenario_issue_date": "2021-03-12T09:37:43+01:00"
    },
    {
        "fix_commit_hash": "818251fc8519167be7e0730083c4a694972fb06b",
        "repo_name": "superset",
        "best_scenario_issue_date": "2017-05-11T20:32:05-07:00"
    },
    {
        "fix_commit_hash": "0472c11157450de50cd97e36e4459bb2c9c4e5e4",
        "repo_name": "superset",
        "best_scenario_issue_date": "2020-04-18T20:29:57+03:00"
    },
    {
        "fix_commit_hash": "83ec7365a7b369e6490a7eb666cfdb51e44d542d",
        "repo_name": "superset",
        "best_scenario_issue_date": "2020-05-12T18:16:53-07:00"
    },
    {
        "fix_commit_hash": "ba8c619c2e8ca9f7726b0bb879b0ede0ef9582a2",
        "repo_name": "superset",
        "best_scenario_issue_date": "2020-07-02T17:47:54-07:00"
    },
    {
        "fix_commit_hash": "09f407f553eb8bca90f6da79cf60c742296488c7",
        "repo_name": "superset",
        "best_scenario_issue_date": "2017-04-12T13:25:07-07:00"
    }
]